[
  { "id": 1,
    "name": "Apple Watch Series 9",
    "brand": "Apple",
    "price": 399,
    "image": "https://m.media-amazon.com/images/I/71aXGgNCE9L.jpg",
    "description": "Apple Watch Series 9, smart wearable with fitness tracking, notifications, and health monitoring."
  },
  { "id": 2,
    "name": "Galaxy Watch 6",
    "brand": "Samsung",
    "price": 349,
    "image": "https://cairosales.com/103722-large_default/samsung-galaxy-watch-6-bluetooth-44-mm-graphite-sm-r940nzkamea.jpg",
    "description": "Samsung Galaxy Watch 6, advanced smartwatch with fitness features, heart rate monitoring, and customizable watch faces."
  },
  { "id": 3,
    "name": "Oppo Watch 3",
    "brand": "Oppo",
    "price": 229,
    "image": "https://mobilecoom.com/wp-content/uploads/2023/06/Oppo-Watch-3-Pro.png",
    "description": "Oppo Watch 3, stylish smartwatch with AMOLED display, health tracking, and long battery life."
  },
  { "id": 4,
    "name": "Huawei Band 8",
    "brand": "Huawei",
    "price": 79,
    "image": "https://api.mobilaty.com/storage/uploads/band8-green-1-1685024292.jpg",
    "description": "Huawei Band 8, lightweight fitness tracker with heart rate monitoring and sleep tracking features."
  },
  { "id": 5,
    "name": "Sony WH-1000XM5",
    "brand": "Sony",
    "price": 399,
    "image": "https://m.media-amazon.com/images/I/61ULAZmt9NL.jpg",
    "description": "Sony WH-1000XM5, premium noise-cancelling wireless headphones with excellent sound quality and comfort."
  },
  { "id": 6,
    "name": "Beats Studio3",
    "brand": "Apple",
    "price": 349,
    "image": "https://cdnp.cody.mn/spree/images/2285211/zoom/82.Beats_Studio3_-_Blue_1.jpg?1712033280",
    "description": "Beats Studio3 wireless headphones with active noise cancelling, deep bass, and long battery life."
  },
  { "id": 7,
    "name": "JBL Flip 6",
    "brand": "JBL",
    "price": 129,
    "image": "https://i5.walmartimages.com/asr/2dd13223-4c5b-42b4-a5ab-4739a02824e9.673a62d9c54b389b59d40967ff9a6545.jpeg",
    "description": "JBL Flip 6 portable Bluetooth speaker with rich sound, waterproof design, and long battery life."
  },
  { "id": 8,
    "name": "Realme Buds Q3",
    "brand": "Realme",
    "price": 49,
    "image": "https://m.media-amazon.com/images/I/51eULLtKbIL._UF1000,1000_QL80_.jpg",
    "description": "Realme Buds Q3, affordable wireless earbuds with clear sound, low latency, and touch controls."
  },
  { "id": 9,
    "name": "Infinix InPods 12",
    "brand": "Infinix",
    "price": 39,
    "image": "https://www.smartgadgets.com.co/cdn/shop/files/CopiadeFormatoCelular_Watch-2025-09-11T155136.227_48501973-caa8-496b-b3b5-1a213c287a36.jpg?v=1758572375&width=1445",
    "description": "Infinix InPods 12 wireless earbuds, lightweight and compact with decent sound quality and battery life."
  },
  { "id": 10,
    "name": "Dell USB-C Charger 65W",
    "brand": "Dell",
    "price": 59,
    "image": "https://macfixegypt.com/wp-content/uploads/2021/12/1-11.jpg",
    "description": "Dell 65W USB-C charger, compact and fast-charging for laptops and compatible devices."
  },
  { "id": 11,
    "name": "HP 45W USB-C Charger",
    "brand": "HP",
    "price": 49,
    "image": "https://macfixegypt.com/wp-content/uploads/2021/12/1-18.jpg",
    "description": "HP 45W USB-C charger, reliable and compact, perfect for HP laptops and other compatible devices."
  },
  { "id": 12,
    "name": "Acer USB-C Charger 65W",
    "brand": "Acer",
    "price": 55,
    "image": "https://m.media-amazon.com/images/I/61HCXe5em2L._AC_SL1500_.jpg",
    "description": "Acer USB-C 65W charger, compact design and fast charging for laptops and compatible devices."
  },
  { "id": 13,
    "name": "ASUS ROG Delta Headset",
    "brand": "ASUS",
    "price": 199,
    "image": "https://cdn.cs.1worldsync.com/8c/be/8cbeaba1-85d6-43da-ab4f-1ab33fa8eb93.jpg",
    "description": "ASUS ROG Delta gaming headset with high-quality audio, comfortable design, and customizable RGB lighting."
  },
  { "id": 14,
    "name": "MSI Immerse GH50",
    "brand": "MSI",
    "price": 149,
    "image": "https://www.bhphotovideo.com/images/fb/msi_immerse_gh50_gaming_headset_1513000.jpg",
    "description": "MSI Immerse GH50, gaming headset with immersive sound, noise cancellation, and lightweight design."
  },
  { "id": 15,
    "name": "Toshiba USB-C Hub",
    "brand": "Toshiba",
    "price": 69,
    "image": "https://m.media-amazon.com/images/I/41tSha0LBTL.jpg",
    "description": "Toshiba USB-C hub with multiple ports for easy connectivity of laptops and devices."
  },
  { "id": 16,
    "name": "Xiaomi Mi Band 8",
    "brand": "Xiaomi",
    "price": 49,
    "image": "https://encrypted-tbn0.gstatic.com/images?q=tbn:ANd9GcQlPuuW3qB6kfWitZBOwNgsuNMaN7c6lE-aDg&s",
    "description": "Xiaomi Mi Band 8, affordable fitness tracker with heart rate monitoring, notifications, and sleep tracking."
  },
  { "id": 17,
    "name": "Realme Watch 3",
    "brand": "Realme",
    "price": 69,
    "image": "https://cdn.tgdd.vn/Products/Images/7077/287056/realme-watch-3-day-silicone-den-1-750x500.jpg",
    "description": "Realme Watch 3, budget-friendly smartwatch with fitness features, heart rate sensor, and notifications."
  },
  { "id": 18,
    "name": "Infinix Smart Watch X1",
    "brand": "Infinix",
    "price": 59,
    "image": "https://encrypted-tbn0.gstatic.com/images?q=tbn:ANd9GcTzkwM6-OBwfOygrUu8-99dmt8TMLj0QX15dg&s",
    "description": "Infinix Smart Watch X1, affordable wearable with health tracking and notifications for daily use."
  },
  { "id": 19,
    "name": "Logitech MX Master 3 Mouse",
    "brand": "Logitech",
    "price": 99,
    "image": "https://tv-it.com/storage/shada/logitech-1/logitech-mx-master-3s-mouse-p1.webp",
    "description": "Logitech MX Master 3, ergonomic wireless mouse with high precision and customizable buttons for productivity."
  },
  { "id": 20,
    "name": "Logitech K780 Keyboard",
    "brand": "Logitech",
    "price": 79,
    "image": "https://egyptlaptop.com/images/detailed/76/logitech_keyboard_wireless.webp",
    "description": "Logitech K780, multi-device wireless keyboard with comfortable typing and integrated number pad."
  },
  { "id": 21,
    "name": "Razer DeathAdder V2",
    "brand": "Razer",
    "price": 69,
    "image": "https://encrypted-tbn0.gstatic.com/images?q=tbn:ANd9GcSNByyQP_Vc8vcuuKFbak2Dukhwy7fdO1zSWg&s",
    "description": "Razer DeathAdder V2, high-performance gaming mouse with ergonomic design and customizable RGB lighting."
  },
  { "id": 22,
    "name": "Razer BlackWidow V3",
    "brand": "Razer",
    "price": 139,
    "image": "https://media.ldlc.com/r1600/ld/products/00/05/73/21/LD0005732116_1.jpg",
    "description": "Razer BlackWidow V3 mechanical keyboard, designed for gaming with tactile switches and RGB lighting."
  },
  { "id": 23,
    "name": "Logitech C920 Webcam",
    "brand": "Logitech",
    "price": 79,
    "image": "https://tv-it.com/storage/shada/logitech-1/webcam-logitech-fhd-c920-pro-p2.webp",
    "description": "Logitech C920, high-definition webcam with clear video quality and built-in stereo microphone."
  },
  { "id": 24,
    "name": "Anker PowerPort 4 USB Charger",
    "brand": "Anker",
    "price": 39,
    "image": "https://www.c2wireless.com/cdn/shop/products/media_76de1eaa-da21-4eac-8ee3-bf2eb573abe9_1024x1024.jpg?v=1688587118",
    "description": "Anker PowerPort 4, compact multi-port USB charger with fast charging capability for multiple devices."
  },
  { "id": 25,
    "name": "HyperX Alloy FPS Keyboard",
    "brand": "HyperX",
    "price": 99,
    "image": "https://encrypted-tbn0.gstatic.com/images?q=tbn:ANd9GcTFiJfYDE9VFEdGELEfdEcnT918-uH5SqnFJw&s",
    "description": "HyperX Alloy FPS, mechanical gaming keyboard with red switches and compact design for fast response."
  },
  { "id": 26,
    "name": "Seagate Portable 2TB HDD",
    "brand": "Seagate",
    "price": 69,
    "image": "https://img.overclockers.co.uk/images/HD-3CP-SE/9796ce05cc56ddacebe27158f4e1aa4f.jpg",
    "description": "Seagate 2TB portable external hard drive, compact design with fast data transfer and reliable storage."
  },
  { "id": 27,
    "name": "WD My Passport 4TB",
    "brand": "Western Digital",
    "price": 119,
    "image": "https://encrypted-tbn0.gstatic.com/images?q=tbn:ANd9GcTKTjl09WhKpY5K_hEPuB0ENWSHMg4xBNQf4g&s",
    "description": "WD My Passport 4TB, portable external hard drive with password protection and high-speed USB connectivity."
  },
  { "id": 28,
    "name": "Logitech G Pro X Superlight Mouse",
    "brand": "Logitech",
    "price": 149,
    "image": "https://elbadrgroupeg.store/image/cache/catalog/logitech/PUD92JblkkR03B4kmgM8t7kSgpR3tC2RKRDxfyeONTK7j9UCCLl5fwXZ0-1384x1038.png",
    "description": "Logitech G Pro X Superlight, ultra-lightweight gaming mouse with high accuracy and wireless connectivity."
  },
  { "id": 29,
    "name": "Corsair K95 RGB Platinum Keyboard",
    "brand": "Corsair",
    "price": 199,
    "image": "https://www.vedantcomputers.com/image/cache/catalog/assets/product/corsair/keyboard/ch-9127012-na/ch-9127012-na-1-550x550.jpg",
    "description": "Corsair K95 RGB Platinum, mechanical gaming keyboard with programmable keys and vibrant RGB lighting."
  },
  { "id": 30,
    "name": "Elgato Stream Deck",
    "brand": "Elgato",
    "price": 149,
    "image": "https://res.cloudinary.com/elgato-pwa/image/upload/q_auto,f_auto/pg_name:10GBA9901;10GBA9901/f_auto/q_auto/v1756981681/2025/Stream%20Deck%20Classic/01_ATF/01_ATFs_static_003_Mobile.psd",
    "description": "Elgato Stream Deck, customizable control panel with LCD keys, ideal for streamers and content creators."
  }
]